exofop/__init__.py
exofop/config/__init__.py
exofop/config/style.mplstyle
exofop/config/synonym_map_lc.yaml
exofop/cookies/exofop_cookies_lovelace_0.txt
exofop/download/__init__.py
exofop/download/async_downloader.py
exofop/download/authenticator.py
exofop/download/cookie_manager.py
exofop/download/downloaders.py
exofop/download/identifiers.py
exofop/extract/__init__.py
exofop/extract/extractor.py
exofop/extract/load_exofop_measurements_file.py
exofop/extract/parse_exofop_file_name.py
exofop/extract/synonym_map.py
exofop/utils/__init__.py
exofop/utils/logger.py
exofop/utils/paths.py
exofop/utils/timer.py
exofop/utils/urls.py
exofop-0.0.2.dist-info/LICENSE
exofop-0.0.2.dist-info/METADATA
exofop-0.0.2.dist-info/WHEEL
exofop-0.0.2.dist-info/top_level.txt
exofop-0.0.2.dist-info/RECORD
