Metadata-Version: 2.1
Name: exofop
Version: 0.0.2
Summary: Generic light curve object
Author-email: David Degen <ddegen@ethz.ch>
License: MIT
Project-URL: Homepage, https://dgegen.github.io/exofop/
Project-URL: Source, https://github.com/dgegen/exofop
Project-URL: Bug Tracker, https://github.com/dgegen/exofop/issues
Keywords: astronomy,astrophysics,time series analysis,lightcurves,ExoFOP
Classifier: Programming Language :: Python :: 3
Requires-Python: >=3.9
License-File: LICENSE
Requires-Dist: aiofiles
Requires-Dist: astropy
Requires-Dist: numpy
Requires-Dist: pandas
Requires-Dist: httpx
Requires-Dist: tqdm
Provides-Extra: all
Requires-Dist: lightkurve ; extra == 'all'
Provides-Extra: dev
Requires-Dist: nox ; extra == 'dev'
Requires-Dist: ruff ; extra == 'dev'
Requires-Dist: black ; extra == 'dev'
Requires-Dist: pytest ; extra == 'dev'
Provides-Extra: docs
Requires-Dist: sphinx ; extra == 'docs'
Requires-Dist: sphinx-book-theme ; extra == 'docs'
Requires-Dist: sphinx-design ; extra == 'docs'
Requires-Dist: sphinx-copybutton ; extra == 'docs'
Requires-Dist: ipython ; extra == 'docs'
Requires-Dist: matplotlib ; extra == 'docs'
Requires-Dist: notebook ; extra == 'docs'
Requires-Dist: ipywidgets ; extra == 'docs'
Requires-Dist: myst-nb ; extra == 'docs'
Requires-Dist: ghp-import ; extra == 'docs'
Provides-Extra: test
Requires-Dist: pytest ; extra == 'test'
Requires-Dist: pytest-asyncio ; extra == 'test'
Requires-Dist: pytest-xdist ; extra == 'test'
Provides-Extra: visualization
Requires-Dist: ipython ; extra == 'visualization'
Requires-Dist: matplotlib ; extra == 'visualization'
Requires-Dist: notebook ; extra == 'visualization'
Requires-Dist: ipywidgets ; extra == 'visualization'
